README.rst
setup.py
ws_grid_pager/__init__.py
ws_grid_pager/grid_pager.py
ws_grid_pager/grid_pager_send_window.py
ws_grid_pager/grid_pager_switch_workspace.py
ws_grid_pager/grid_pager_take_window.py
ws_grid_pager/ws_grid_pager.py
ws_grid_pager.egg-info/PKG-INFO
ws_grid_pager.egg-info/SOURCES.txt
ws_grid_pager.egg-info/dependency_links.txt
ws_grid_pager.egg-info/entry_points.txt
ws_grid_pager.egg-info/top_level.txt