Metadata-Version: 1.1
Name: ws-grid-pager
Version: 0.2
Summary: A workspace grid pager for EMWH-compliant window-managers
Home-page: https://github.com/ckot/ws-grid-pager
Author: Scott Silliman
Author-email: scott.t.silliman@gmail.com
License: GNU General Public License v2 (GPLv2)
Download-URL: https://github.com/ckot/ws-grid-pager/archive/master.zip
Platform: UNKNOWN
Classifier: Development Status :: 4 - Beta
Classifier: Environment :: Console
Classifier: Intended Audience :: Other Audience
Classifier: License :: OSI Approved :: GNU General Public License v2 (GPLv2)
Classifier: Natural Language :: English
Classifier: Operating System :: POSIX :: Linux
Classifier: Programming Language :: Python
Classifier: Programming Language :: Python :: 2
Classifier: Programming Language :: Python :: 2.7
Classifier: Topic :: Desktop Environment :: Window Managers
Classifier: Topic :: Desktop Environment :: Window Managers :: Fluxbox
